README.txt
setup.cfg
setup.py
pyjon/__init__.py
pyjon.versionning.egg-info/PKG-INFO
pyjon.versionning.egg-info/SOURCES.txt
pyjon.versionning.egg-info/dependency_links.txt
pyjon.versionning.egg-info/entry_points.txt
pyjon.versionning.egg-info/namespace_packages.txt
pyjon.versionning.egg-info/not-zip-safe
pyjon.versionning.egg-info/requires.txt
pyjon.versionning.egg-info/top_level.txt
pyjon/versionning/__init__.py
pyjon/versionning/base.py
pyjon/versionning/initialization.py
pyjon/versionning/sqlalchemy.py