Metadata-Version: 1.0
Name: pyjon.versionning
Version: 0.4.2
Summary: Versionning system taking Python objects (likely from an ORM like SQL Alchemy) and saving those objects in a repository with synchronisation facility.
Home-page: UNKNOWN
Author: Jonathan Schemoul
Author-email: jonathan.schemoul@gmail.com
License: MIT
Keywords: versionning mercurial sqlalchemy web
Platform: UNKNOWN
Classifier: Programming Language :: Python
Classifier: Topic :: Software Development :: Libraries :: Python Modules
